{
  "chains": [
    {
      "chain": "EXPORT_MODULE_PDF",
      "description": "Exportiert aktuelle Reflexausgabe als PDF",
      "path_trigger": "/html/VIRENNA_CEO_Dashboard_Siegel_Inline.html",
      "output_format": "pdf",
      "enabled_for": ["ReflexEngine", "Jake_Assistant"]
    },
    {
      "chain": "AUDIT_SUMMARY_EXPORT",
      "description": "xyz (testlauf)",
      "path_trigger": "/logs/audit-gpt-access.json",
      "output_format": "json",
      "enabled_for": ["Jake_Assistant"]
    }
  ]
}
